{
  "Date": "November 2012",
  "Tournament": "2012 YCS Seattle",
  "DeckName": "Agents_",
  "DeckId": "1965",
  "Duelist": "Simon He",
  "Placed": "5th - 8th Place",
  "Archetype": "Agent",
  "DeckProfile": "www.youtube.com/embed/xRlgzfsKcDU",
  "MainDeck": [
    {
      "Name": "Archlord Kristya",
      "Copies": 1
    },
    {
      "Name": "Black Luster Soldier - Envoy of the Beginning",
      "Copies": 1
    },
    {
      "Name": "Chaos Sorcerer",
      "Copies": 1
    },
    {
      "Name": "Effect Veiler",
      "Copies": 2
    },
    {
      "Name": "Gorz the Emissary of Darkness",
      "Copies": 1
    },
    {
      "Name": "Herald of Orange Light",
      "Copies": 1
    },
    {
      "Name": "Honest",
      "Copies": 1
    },
    {
      "Name": "Master Hyperion",
      "Copies": 3
    },
    {
      "Name": "Maxx \"C\"",
      "Copies": 2
    },
    {
      "Name": "Mystical Shine Ball",
      "Copies": 3
    },
    {
      "Name": "Sangan",
      "Copies": 1
    },
    {
      "Name": "Spirit Reaper",
      "Copies": 1
    },
    {
      "Name": "The Agent of Creation - Venus",
      "Copies": 3
    },
    {
      "Name": "The Agent of Mystery - Earth",
      "Copies": 2
    },
    {
      "Name": "Thunder King Rai-Oh",
      "Copies": 2
    },
    {
      "Name": "Tour Guide From the Underworld",
      "Copies": 2
    },
    {
      "Name": "Tragoedia",
      "Copies": 2
    },
    {
      "Name": "Creature Swap",
      "Copies": 1
    },
    {
      "Name": "Dark Hole",
      "Copies": 1
    },
    {
      "Name": "Enemy Controller",
      "Copies": 1
    },
    {
      "Name": "Forbidden Lance",
      "Copies": 1
    },
    {
      "Name": "Heavy Storm",
      "Copies": 1
    },
    {
      "Name": "Mind Control",
      "Copies": 1
    },
    {
      "Name": "Monster Reborn",
      "Copies": 1
    },
    {
      "Name": "Mystical Space Typhoon",
      "Copies": 3
    },
    {
      "Name": "Treacherous Trap Hole",
      "Copies": 1
    }
  ],
  "ExtraDeck": [
    {
      "Name": "Ally of Justice Catastor",
      "Copies": 1
    },
    {
      "Name": "Armory Arm",
      "Copies": 1
    },
    {
      "Name": "Black Rose Dragon",
      "Copies": 1
    },
    {
      "Name": "Daigusto Phoenix",
      "Copies": 1
    },
    {
      "Name": "Gachi Gachi Gantetsu",
      "Copies": 1
    },
    {
      "Name": "Hieratic Sun Dragon Overlord of Heliopolis",
      "Copies": 1
    },
    {
      "Name": "Leviair the Sea Dragon",
      "Copies": 1
    },
    {
      "Name": "Number 17: Leviathan Dragon",
      "Copies": 1
    },
    {
      "Name": "Number 30: Acid Golem of Destruction",
      "Copies": 1
    },
    {
      "Name": "Number 96: Dark Mist",
      "Copies": 1
    },
    {
      "Name": "Stardust Dragon",
      "Copies": 1
    },
    {
      "Name": "Superdreadnought Rail Cannon Gustav Max",
      "Copies": 1
    },
    {
      "Name": "Temtempo the Percussion Djinn",
      "Copies": 1
    },
    {
      "Name": "Wind-Up Zenmaines",
      "Copies": 1
    },
    {
      "Name": "Ally of Justice Catastor",
      "Copies": 1
    },
    {
      "Name": "Armory Arm",
      "Copies": 1
    },
    {
      "Name": "Black Rose Dragon",
      "Copies": 1
    },
    {
      "Name": "Gaia Knight, the Force of Earth",
      "Copies": 1
    },
    {
      "Name": "Stardust Dragon",
      "Copies": 1
    }
  ],
  "SideDeck": [
    {
      "Name": "Chimeratech Fortress Dragon",
      "Copies": 1
    },
    {
      "Name": "Cyber Dragon",
      "Copies": 1
    },
    {
      "Name": "Dark Magician",
      "Copies": 1
    },
    {
      "Name": "Electric Virus",
      "Copies": 1
    },
    {
      "Name": "Gemini Imps",
      "Copies": 2
    },
    {
      "Name": "Leeching the Light",
      "Copies": 1
    },
    {
      "Name": "Nobleman of Crossout",
      "Copies": 2
    },
    {
      "Name": "Gozen Match",
      "Copies": 2
    },
    {
      "Name": "Royal Decree",
      "Copies": 2
    },
    {
      "Name": "Soul Drain",
      "Copies": 2
    }
  ]
}