{
  "Date": "August 2019",
  "Tournament": "Regional - S. Portland Maine",
  "DeckName": "True Draco",
  "DeckId": "8120",
  "Duelist": "Ben Rosen",
  "Placed": "5th Place",
  "Archetype": "True Draco",
  "DeckProfile": "www.youtube.com/embed/BKtIwazU8GQ",
  "MainDeck": [
    {
      "Name": "Dinomight Knight, the True Dracofighter",
      "Copies": 1
    },
    {
      "Name": "Ignis Heat, the True Dracowarrior",
      "Copies": 3
    },
    {
      "Name": "Majesty Maiden, the True Dracocaster",
      "Copies": 1
    },
    {
      "Name": "Card of Demise",
      "Copies": 3
    },
    {
      "Name": "Disciples of the True Dracophoenix",
      "Copies": 3
    },
    {
      "Name": "Dragonic Diagram",
      "Copies": 3
    },
    {
      "Name": "Pot of Duality",
      "Copies": 2
    },
    {
      "Name": "Terraforming",
      "Copies": 1
    },
    {
      "Name": "True Draco Heritage",
      "Copies": 3
    },
    {
      "Name": "Crackdown",
      "Copies": 2
    },
    {
      "Name": "Infinite Impermanence",
      "Copies": 3
    },
    {
      "Name": "Solemn Judgment",
      "Copies": 2
    },
    {
      "Name": "Summon Limit",
      "Copies": 3
    },
    {
      "Name": "The Monarchs Erupt",
      "Copies": 3
    },
    {
      "Name": "There Can Be Only One",
      "Copies": 3
    },
    {
      "Name": "True Draco Apocalypse",
      "Copies": 3
    },
    {
      "Name": "True King's Return",
      "Copies": 1
    }
  ],
  "ExtraDeck": [],
  "SideDeck": [
    {
      "Name": "Gameciel, the Sea Turtle Kaiju",
      "Copies": 3
    },
    {
      "Name": "Metaltron XII, the True Dracombatant",
      "Copies": 1
    },
    {
      "Name": "The Winged Dragon of Ra - Sphere Mode",
      "Copies": 3
    },
    {
      "Name": "Anti-Spell Fragrance",
      "Copies": 3
    },
    {
      "Name": "Evenly Matched",
      "Copies": 3
    },
    {
      "Name": "Unending Nightmare",
      "Copies": 2
    }
  ]
}