{
  "Date": "December 2016",
  "Tournament": "YCS - Bochum Germany",
  "DeckName": "Burning Abyss",
  "DeckId": "7345",
  "Duelist": "Fotios Papadoliakos",
  "Placed": "Top 16",
  "Archetype": "Burning Abyss",
  "DeckProfile": "www.youtube.com/embed/0BWCBKkaSrA",
  "MainDeck": [
    {
      "Name": "Alich, Malebranche of the Burning Abyss",
      "Copies": 1
    },
    {
      "Name": "Barbar, Malebranche of the Burning Abyss",
      "Copies": 1
    },
    {
      "Name": "Calcab, Malebranche of the Burning Abyss",
      "Copies": 1
    },
    {
      "Name": "Cir, Malebranche of the Burning Abyss",
      "Copies": 1
    },
    {
      "Name": "Fairy Tail - Snow",
      "Copies": 1
    },
    {
      "Name": "Farfa, Malebranche of the Burning Abyss",
      "Copies": 3
    },
    {
      "Name": "Fiendish Rhino Warrior",
      "Copies": 1
    },
    {
      "Name": "Ghost Reaper & Winter Cherries",
      "Copies": 3
    },
    {
      "Name": "Graff, Malebranche of the Burning Abyss",
      "Copies": 1
    },
    {
      "Name": "Libic, Malebranche of the Burning Abyss",
      "Copies": 1
    },
    {
      "Name": "Maxx \"C\"",
      "Copies": 2
    },
    {
      "Name": "Rubic, Malebranche of the Burning Abyss",
      "Copies": 1
    },
    {
      "Name": "Scarm, Malebranche of the Burning Abyss",
      "Copies": 3
    },
    {
      "Name": "Speedroid Taketomborg",
      "Copies": 1
    },
    {
      "Name": "Speedroid Terrortop",
      "Copies": 3
    },
    {
      "Name": "Tour Guide From the Underworld",
      "Copies": 1
    },
    {
      "Name": "Vanity's Fiend",
      "Copies": 2
    },
    {
      "Name": "Foolish Burial",
      "Copies": 1
    },
    {
      "Name": "Raigeki",
      "Copies": 1
    },
    {
      "Name": "Soul Charge",
      "Copies": 1
    },
    {
      "Name": "Twin Twisters",
      "Copies": 3
    },
    {
      "Name": "Dimensional Barrier",
      "Copies": 2
    },
    {
      "Name": "Karma Cut",
      "Copies": 2
    },
    {
      "Name": "Solemn Strike",
      "Copies": 2
    },
    {
      "Name": "Solemn Warning",
      "Copies": 1
    }
  ],
  "ExtraDeck": [
    {
      "Name": "ABC-Dragon Buster",
      "Copies": 1
    },
    {
      "Name": "Beatrice, Lady of the Eternal",
      "Copies": 1
    },
    {
      "Name": "Blue-Eyes Spirit Dragon",
      "Copies": 1
    },
    {
      "Name": "Dante, Pilgrim of the Burning Abyss",
      "Copies": 1
    },
    {
      "Name": "Dante, Traveler of the Burning Abyss",
      "Copies": 3
    },
    {
      "Name": "Leviair the Sea Dragon",
      "Copies": 1
    },
    {
      "Name": "Masked HERO Dark Law",
      "Copies": 1
    },
    {
      "Name": "Michael, the Arch-Lightsworn",
      "Copies": 1
    },
    {
      "Name": "Number F0: Utopic Future",
      "Copies": 1
    },
    {
      "Name": "Super Quantal Mech Beast Grampulse",
      "Copies": 1
    },
    {
      "Name": "The Phantom Knights of Break Sword",
      "Copies": 1
    },
    {
      "Name": "Toadally Awesome",
      "Copies": 1
    },
    {
      "Name": "Virgil, Rock Star of the Burning Abyss",
      "Copies": 1
    }
  ],
  "SideDeck": [
    {
      "Name": "Flying \"C\"",
      "Copies": 2
    },
    {
      "Name": "Gameciel, the Sea Turtle Kaiju",
      "Copies": 2
    },
    {
      "Name": "Jinzo",
      "Copies": 3
    },
    {
      "Name": "Vanity's Fiend",
      "Copies": 1
    },
    {
      "Name": "Enemy Controller",
      "Copies": 2
    },
    {
      "Name": "System Down",
      "Copies": 2
    },
    {
      "Name": "Anti-Spell Fragrance",
      "Copies": 3
    }
  ]
}