{
  "Date": "March 2015",
  "Tournament": "Regional - Lisbon Portugal",
  "DeckName": "Qliphorts",
  "DeckId": "4086",
  "Duelist": "Gleb Trubitcoi",
  "Placed": "5th - 8th Place",
  "Archetype": "Qliphort",
  "DeckProfile": "",
  "MainDeck": [
    {
      "Name": "Apoqliphort Towers",
      "Copies": 1
    },
    {
      "Name": "Performapal Trampolynx",
      "Copies": 2
    },
    {
      "Name": "Qliphort Carrier",
      "Copies": 3
    },
    {
      "Name": "Qliphort Disk",
      "Copies": 3
    },
    {
      "Name": "Qliphort Helix",
      "Copies": 3
    },
    {
      "Name": "Qliphort Scout",
      "Copies": 3
    },
    {
      "Name": "Qliphort Stealth",
      "Copies": 1
    },
    {
      "Name": "Book of Moon",
      "Copies": 1
    },
    {
      "Name": "Mystical Space Typhoon",
      "Copies": 3
    },
    {
      "Name": "Raigeki",
      "Copies": 1
    },
    {
      "Name": "Saqlifice",
      "Copies": 3
    },
    {
      "Name": "Snatch Steal",
      "Copies": 1
    },
    {
      "Name": "Summoner's Art",
      "Copies": 3
    },
    {
      "Name": "Upstart Goblin",
      "Copies": 3
    },
    {
      "Name": "Mirror Force",
      "Copies": 3
    },
    {
      "Name": "Skill Drain",
      "Copies": 3
    },
    {
      "Name": "Vanity's Emptiness",
      "Copies": 3
    }
  ],
  "ExtraDeck": [
    {
      "Name": "Abyss Dweller",
      "Copies": 1
    },
    {
      "Name": "Castel, the Skyblaster Musketeer",
      "Copies": 1
    },
    {
      "Name": "Diamond Dire Wolf",
      "Copies": 1
    },
    {
      "Name": "Divine Dragon Knight Felgrand",
      "Copies": 1
    },
    {
      "Name": "Evilswarm Exciton Knight",
      "Copies": 1
    },
    {
      "Name": "Gagaga Cowboy",
      "Copies": 1
    },
    {
      "Name": "Mecha Phantom Beast Dracossack",
      "Copies": 1
    },
    {
      "Name": "Number 101: Silent Honor ARK",
      "Copies": 1
    },
    {
      "Name": "Number 11: Big Eye",
      "Copies": 1
    },
    {
      "Name": "Number 50: Blackship of Corn",
      "Copies": 1
    },
    {
      "Name": "Number 61: Volcasaurus",
      "Copies": 1
    },
    {
      "Name": "Number 82: Heartlandraco",
      "Copies": 1
    },
    {
      "Name": "Number 85: Crazy Box",
      "Copies": 1
    },
    {
      "Name": "Photon Papilloperative",
      "Copies": 1
    },
    {
      "Name": "Stardust Dragon",
      "Copies": 1
    }
  ],
  "SideDeck": [
    {
      "Name": "Abyss Dweller",
      "Copies": 1
    },
    {
      "Name": "Castel, the Skyblaster Musketeer",
      "Copies": 1
    },
    {
      "Name": "Diamond Dire Wolf",
      "Copies": 1
    },
    {
      "Name": "Divine Dragon Knight Felgrand",
      "Copies": 1
    },
    {
      "Name": "Evilswarm Exciton Knight",
      "Copies": 1
    },
    {
      "Name": "Gagaga Cowboy",
      "Copies": 1
    },
    {
      "Name": "Mecha Phantom Beast Dracossack",
      "Copies": 1
    },
    {
      "Name": "Number 101: Silent Honor ARK",
      "Copies": 1
    },
    {
      "Name": "Number 11: Big Eye",
      "Copies": 1
    },
    {
      "Name": "Number 50: Blackship of Corn",
      "Copies": 1
    },
    {
      "Name": "Number 61: Volcasaurus",
      "Copies": 1
    },
    {
      "Name": "Number 82: Heartlandraco",
      "Copies": 1
    },
    {
      "Name": "Number 85: Crazy Box",
      "Copies": 1
    },
    {
      "Name": "Photon Papilloperative",
      "Copies": 1
    },
    {
      "Name": "Stardust Dragon",
      "Copies": 1
    }
  ]
}