{
  "Date": "September 2018",
  "Tournament": "Dueling Book Tournament",
  "DeckName": "Danger!",
  "DeckId": "8891",
  "Duelist": "Just_a_mongrel",
  "Placed": "3rd Place",
  "Archetype": "Danger!",
  "DeckProfile": "",
  "MainDeck": [
    {
      "Name": "Ash Blossom & Joyous Spring",
      "Copies": 3
    },
    {
      "Name": "Danger! Bigfoot!",
      "Copies": 3
    },
    {
      "Name": "Danger! Chupacabra!",
      "Copies": 3
    },
    {
      "Name": "Danger!? Jackalope?",
      "Copies": 3
    },
    {
      "Name": "Danger! Nessie!",
      "Copies": 3
    },
    {
      "Name": "Destiny HERO - Diamond Dude",
      "Copies": 1
    },
    {
      "Name": "Droll & Lock Bird",
      "Copies": 1
    },
    {
      "Name": "Ghost Ogre & Snow Rabbit",
      "Copies": 1
    },
    {
      "Name": "Morphing Jar",
      "Copies": 1
    },
    {
      "Name": "Allure of Darkness",
      "Copies": 1
    },
    {
      "Name": "Book of Moon",
      "Copies": 1
    },
    {
      "Name": "Card Destruction",
      "Copies": 1
    },
    {
      "Name": "Monster Reborn",
      "Copies": 1
    },
    {
      "Name": "Mystical Space Typhoon",
      "Copies": 2
    },
    {
      "Name": "Raigeki",
      "Copies": 1
    },
    {
      "Name": "Realm of Danger!",
      "Copies": 3
    },
    {
      "Name": "Soul Charge",
      "Copies": 1
    },
    {
      "Name": "Terraforming",
      "Copies": 2
    },
    {
      "Name": "Twin Twisters",
      "Copies": 2
    },
    {
      "Name": "Dark Bribe",
      "Copies": 2
    },
    {
      "Name": "Mirror Force",
      "Copies": 2
    },
    {
      "Name": "Scrap-Iron Scarecrow",
      "Copies": 1
    },
    {
      "Name": "Storming Mirror Force",
      "Copies": 1
    }
  ],
  "ExtraDeck": [
    {
      "Name": "Number 68: Sanaphond the Sky Prison",
      "Copies": 3
    },
    {
      "Name": "Number 85: Crazy Box",
      "Copies": 3
    }
  ],
  "SideDeck": [
    {
      "Name": "Droll & Lock Bird",
      "Copies": 2
    },
    {
      "Name": "Ghost Ogre & Snow Rabbit",
      "Copies": 2
    },
    {
      "Name": "Dark Hole",
      "Copies": 1
    },
    {
      "Name": "Mystical Space Typhoon",
      "Copies": 1
    },
    {
      "Name": "Twin Twisters",
      "Copies": 1
    },
    {
      "Name": "Danger! Zone",
      "Copies": 3
    }
  ]
}