{
  "Date": "December 2022",
  "Tournament": "Regional - Dublin Ireland",
  "DeckName": "Bystial Spright",
  "DeckId": "9393",
  "Duelist": "Charles Kelly",
  "Placed": "2nd Place",
  "Archetype": "Spright",
  "DeckProfile": "www.youtube.com/embed/9KGwV4lx9zc",
  "MainDeck": [
    {
      "Name": "Bystial Druiswurm",
      "Copies": 3
    },
    {
      "Name": "Bystial Magnamhut",
      "Copies": 3
    },
    {
      "Name": "Bystial Saronir",
      "Copies": 3
    },
    {
      "Name": "D.D. Crow",
      "Copies": 3
    },
    {
      "Name": "Nimble Angler",
      "Copies": 2
    },
    {
      "Name": "Nimble Beaver",
      "Copies": 3
    },
    {
      "Name": "Spright Blue",
      "Copies": 3
    },
    {
      "Name": "Spright Carrot",
      "Copies": 1
    },
    {
      "Name": "Spright Jet",
      "Copies": 3
    },
    {
      "Name": "Spright Pixies",
      "Copies": 1
    },
    {
      "Name": "Spright Red",
      "Copies": 1
    },
    {
      "Name": "Swap Frog",
      "Copies": 2
    },
    {
      "Name": "Change of Heart",
      "Copies": 1
    },
    {
      "Name": "Enemy Controller",
      "Copies": 1
    },
    {
      "Name": "Foolish Burial",
      "Copies": 1
    },
    {
      "Name": "Harpie's Feather Duster",
      "Copies": 1
    },
    {
      "Name": "Spright Smashers",
      "Copies": 1
    },
    {
      "Name": "Spright Starter",
      "Copies": 3
    },
    {
      "Name": "Infinite Impermanence",
      "Copies": 3
    },
    {
      "Name": "Spright Double Cross",
      "Copies": 1
    }
  ],
  "ExtraDeck": [
    {
      "Name": "Cat Shark",
      "Copies": 1
    },
    {
      "Name": "Dharc the Dark Charmer, Gloomy",
      "Copies": 1
    },
    {
      "Name": "Divine Arsenal AA-ZEUS - Sky Thunder",
      "Copies": 1
    },
    {
      "Name": "Downerd Magician",
      "Copies": 1
    },
    {
      "Name": "Gigantic Spright",
      "Copies": 2
    },
    {
      "Name": "I:P Masquerena",
      "Copies": 1
    },
    {
      "Name": "Number 29: Mannequin Cat",
      "Copies": 1
    },
    {
      "Name": "Number 65: Djinn Buster",
      "Copies": 1
    },
    {
      "Name": "Onibimaru Soul Sweeper",
      "Copies": 1
    },
    {
      "Name": "Spright Elf",
      "Copies": 2
    },
    {
      "Name": "Spright Sprind",
      "Copies": 1
    },
    {
      "Name": "Toadally Awesome",
      "Copies": 1
    },
    {
      "Name": "Topologic Zeroboros",
      "Copies": 1
    }
  ],
  "SideDeck": [
    {
      "Name": "Red Resonator",
      "Copies": 1
    },
    {
      "Name": "Testudo erat Numen",
      "Copies": 1
    },
    {
      "Name": "Cosmic Cyclone",
      "Copies": 2
    },
    {
      "Name": "Dark Ruler No More",
      "Copies": 3
    },
    {
      "Name": "Lightning Storm",
      "Copies": 2
    },
    {
      "Name": "Zombie World",
      "Copies": 2
    },
    {
      "Name": "Dimensional Barrier",
      "Copies": 3
    },
    {
      "Name": "Evenly Matched",
      "Copies": 1
    }
  ]
}