{
  "Date": "October 2022",
  "Tournament": "Regional - Moncton New Brunswick",
  "DeckName": "Synchro Tearlaments",
  "DeckId": "9166",
  "Duelist": "Jordan Couture",
  "Placed": "6th Place",
  "Archetype": "Synchro",
  "DeckProfile": "www.youtube.com/embed/VToUoFkLyDU",
  "MainDeck": [
    {
      "Name": "Absolute King Back Jack",
      "Copies": 1
    },
    {
      "Name": "Albion the Shrouded Dragon",
      "Copies": 1
    },
    {
      "Name": "Danger!? Jackalope?",
      "Copies": 1
    },
    {
      "Name": "Danger! Nessie!",
      "Copies": 3
    },
    {
      "Name": "Danger!? Tsuchinoko?",
      "Copies": 1
    },
    {
      "Name": "Destiny HERO - Malicious",
      "Copies": 2
    },
    {
      "Name": "Incredible Ecclesia, the Virtuous",
      "Copies": 1
    },
    {
      "Name": "Nibiru, the Primal Being",
      "Copies": 3
    },
    {
      "Name": "Tearlaments Havnis",
      "Copies": 3
    },
    {
      "Name": "Tearlaments Merrli",
      "Copies": 3
    },
    {
      "Name": "Tearlaments Reinoheart",
      "Copies": 2
    },
    {
      "Name": "Tearlaments Scheiren",
      "Copies": 3
    },
    {
      "Name": "The Golden Swordsoul",
      "Copies": 1
    },
    {
      "Name": "Branded in High Spirits",
      "Copies": 3
    },
    {
      "Name": "Instant Fusion",
      "Copies": 1
    },
    {
      "Name": "Primeval Planet Perlereino",
      "Copies": 3
    },
    {
      "Name": "Super Polymerization",
      "Copies": 3
    },
    {
      "Name": "Terraforming",
      "Copies": 1
    },
    {
      "Name": "Infinite Impermanence",
      "Copies": 3
    },
    {
      "Name": "Tearlaments Sulliek",
      "Copies": 1
    }
  ],
  "ExtraDeck": [
    {
      "Name": "Abyss Dweller",
      "Copies": 1
    },
    {
      "Name": "Baronne de Fleur",
      "Copies": 1
    },
    {
      "Name": "Beatrice, Lady of the Eternal",
      "Copies": 1
    },
    {
      "Name": "D.3.S. Frog",
      "Copies": 1
    },
    {
      "Name": "Dharc the Dark Charmer, Gloomy",
      "Copies": 1
    },
    {
      "Name": "Garura, Wings of Resonant Life",
      "Copies": 2
    },
    {
      "Name": "I:P Masquerena",
      "Copies": 1
    },
    {
      "Name": "Knightmare Unicorn",
      "Copies": 1
    },
    {
      "Name": "Mudragon of the Swamp",
      "Copies": 1
    },
    {
      "Name": "Predaplant Dragostapelia",
      "Copies": 1
    },
    {
      "Name": "Spright Elf",
      "Copies": 1
    },
    {
      "Name": "Stardust Charge Warrior",
      "Copies": 1
    },
    {
      "Name": "Tearlaments Kaleido-Heart",
      "Copies": 1
    },
    {
      "Name": "Tearlaments Kitkallos",
      "Copies": 1
    }
  ],
  "SideDeck": [
    {
      "Name": "Droll & Lock Bird",
      "Copies": 3
    },
    {
      "Name": "Cosmic Cyclone",
      "Copies": 2
    },
    {
      "Name": "Dark Ruler No More",
      "Copies": 3
    },
    {
      "Name": "Harpie's Feather Duster",
      "Copies": 1
    },
    {
      "Name": "Evenly Matched",
      "Copies": 3
    },
    {
      "Name": "Paleozoic Dinomischus",
      "Copies": 3
    }
  ]
}