{
  "Date": "September 2022",
  "Tournament": "Regional - Los Angeles California",
  "DeckName": "60-Card Danger! P.U.N.K. Eldlich Tearlaments",
  "DeckId": "9223",
  "Duelist": "Andrew Abdeen",
  "Placed": "8th Place",
  "Archetype": "Tearlaments",
  "DeckProfile": "www.youtube.com/embed/T52tAAO5Gqw",
  "MainDeck": [
    {
      "Name": "Danger! Bigfoot!",
      "Copies": 1
    },
    {
      "Name": "Danger! Chupacabra!",
      "Copies": 1
    },
    {
      "Name": "Danger!? Jackalope?",
      "Copies": 1
    },
    {
      "Name": "Danger! Mothman!",
      "Copies": 1
    },
    {
      "Name": "Danger! Nessie!",
      "Copies": 3
    },
    {
      "Name": "Danger!? Tsuchinoko?",
      "Copies": 1
    },
    {
      "Name": "Destrudo the Lost Dragon's Frisson",
      "Copies": 1
    },
    {
      "Name": "Eldlich the Golden Lord",
      "Copies": 1
    },
    {
      "Name": "Fairy Tail - Snow",
      "Copies": 1
    },
    {
      "Name": "Noh-P.U.N.K. Deer Note",
      "Copies": 1
    },
    {
      "Name": "Noh-P.U.N.K. Foxy Tune",
      "Copies": 1
    },
    {
      "Name": "Noh-P.U.N.K. Ogre Dance",
      "Copies": 3
    },
    {
      "Name": "Noh-P.U.N.K. Ze Amin",
      "Copies": 3
    },
    {
      "Name": "Shinobi Necro",
      "Copies": 1
    },
    {
      "Name": "Tearlaments Havnis",
      "Copies": 3
    },
    {
      "Name": "Tearlaments Merrli",
      "Copies": 3
    },
    {
      "Name": "Tearlaments Reinoheart",
      "Copies": 1
    },
    {
      "Name": "Tearlaments Scheiren",
      "Copies": 3
    },
    {
      "Name": "Called by the Grave",
      "Copies": 1
    },
    {
      "Name": "Dark Ruler No More",
      "Copies": 3
    },
    {
      "Name": "Emergency Teleport",
      "Copies": 3
    },
    {
      "Name": "Foolish Burial",
      "Copies": 1
    },
    {
      "Name": "Galaxy Cyclone",
      "Copies": 1
    },
    {
      "Name": "Instant Fusion",
      "Copies": 1
    },
    {
      "Name": "Primeval Planet Perlereino",
      "Copies": 3
    },
    {
      "Name": "Super Polymerization",
      "Copies": 3
    },
    {
      "Name": "Terraforming",
      "Copies": 1
    },
    {
      "Name": "Anti-Spell Fragrance",
      "Copies": 1
    },
    {
      "Name": "Conquistador of the Golden Land",
      "Copies": 2
    },
    {
      "Name": "Eldlixir of Scarlet Sanguine",
      "Copies": 3
    },
    {
      "Name": "Huaquero of the Golden Land",
      "Copies": 2
    },
    {
      "Name": "Infinite Impermanence",
      "Copies": 3
    },
    {
      "Name": "Tearlaments Sulliek",
      "Copies": 2
    }
  ],
  "ExtraDeck": [
    {
      "Name": "Abyss Dweller",
      "Copies": 1
    },
    {
      "Name": "Baronne de Fleur",
      "Copies": 1
    },
    {
      "Name": "Chaos Ruler, the Chaotic Magical Dragon",
      "Copies": 1
    },
    {
      "Name": "Crystron Halqifibrax",
      "Copies": 1
    },
    {
      "Name": "Curious, the Lightsworn Dominion",
      "Copies": 1
    },
    {
      "Name": "Dharc the Dark Charmer, Gloomy",
      "Copies": 1
    },
    {
      "Name": "Garura, Wings of Resonant Life",
      "Copies": 1
    },
    {
      "Name": "I:P Masquerena",
      "Copies": 1
    },
    {
      "Name": "Knightmare Gryphon",
      "Copies": 1
    },
    {
      "Name": "Mudragon of the Swamp",
      "Copies": 1
    },
    {
      "Name": "Predaplant Dragostapelia",
      "Copies": 1
    },
    {
      "Name": "Spright Elf",
      "Copies": 1
    },
    {
      "Name": "Tearlaments Kaleido-Heart",
      "Copies": 1
    },
    {
      "Name": "Tearlaments Kitkallos",
      "Copies": 1
    },
    {
      "Name": "Topologic Bomber Dragon",
      "Copies": 1
    }
  ],
  "SideDeck": [
    {
      "Name": "Lava Golem",
      "Copies": 3
    },
    {
      "Name": "PSY-Frame Driver",
      "Copies": 1
    },
    {
      "Name": "PSY-Framegear Gamma",
      "Copies": 3
    },
    {
      "Name": "Red Resonator",
      "Copies": 1
    },
    {
      "Name": "Cosmic Cyclone",
      "Copies": 2
    },
    {
      "Name": "Harpie's Feather Duster",
      "Copies": 1
    },
    {
      "Name": "Deck Devastation Virus",
      "Copies": 1
    },
    {
      "Name": "Eradicator Epidemic Virus",
      "Copies": 1
    },
    {
      "Name": "Red Reboot",
      "Copies": 1
    },
    {
      "Name": "Skill Drain",
      "Copies": 1
    }
  ]
}