{
  "Date": "September 2014",
  "Tournament": "YCS - Madrid Spain",
  "DeckName": "Satellarknights",
  "DeckId": "416",
  "Duelist": "Giovanni Paolini",
  "Placed": "17th - 32nd Place",
  "Archetype": "Satellarknight",
  "DeckProfile": "",
  "MainDeck": [
    {
      "Name": "Satellarknight Altair",
      "Copies": 3
    },
    {
      "Name": "Satellarknight Deneb",
      "Copies": 3
    },
    {
      "Name": "Satellarknight Unukalhai",
      "Copies": 3
    },
    {
      "Name": "Satellarknight Vega",
      "Copies": 2
    },
    {
      "Name": "Mystical Space Typhoon",
      "Copies": 2
    },
    {
      "Name": "Reinforcement of the Army",
      "Copies": 2
    },
    {
      "Name": "Soul Charge",
      "Copies": 3
    },
    {
      "Name": "Upstart Goblin",
      "Copies": 3
    },
    {
      "Name": "Breakthrough Skill",
      "Copies": 2
    },
    {
      "Name": "Call of the Haunted",
      "Copies": 3
    },
    {
      "Name": "Compulsory Evacuation Device",
      "Copies": 1
    },
    {
      "Name": "Dimensional Prison",
      "Copies": 3
    },
    {
      "Name": "Solemn Warning",
      "Copies": 1
    },
    {
      "Name": "Soul Drain",
      "Copies": 1
    },
    {
      "Name": "Stellarnova Alpha",
      "Copies": 3
    },
    {
      "Name": "Vanity's Emptiness",
      "Copies": 3
    },
    {
      "Name": "Wiretap",
      "Copies": 2
    }
  ],
  "ExtraDeck": [
    {
      "Name": "Abyss Dweller",
      "Copies": 2
    },
    {
      "Name": "Cairngorgon, Antiluminescent Knight",
      "Copies": 1
    },
    {
      "Name": "Castel, the Skyblaster Musketeer",
      "Copies": 2
    },
    {
      "Name": "Daigusto Emeral",
      "Copies": 1
    },
    {
      "Name": "Evilswarm Exciton Knight",
      "Copies": 1
    },
    {
      "Name": "Gagaga Cowboy",
      "Copies": 1
    },
    {
      "Name": "Heroic Champion - Excalibur",
      "Copies": 1
    },
    {
      "Name": "Number 101: Silent Honor ARK",
      "Copies": 1
    },
    {
      "Name": "Number 106: Giant Hand",
      "Copies": 1
    },
    {
      "Name": "Number 80: Rhapsody in Berserk",
      "Copies": 1
    },
    {
      "Name": "Stardust Dragon",
      "Copies": 1
    },
    {
      "Name": "Stellarknight Delteros",
      "Copies": 1
    },
    {
      "Name": "Wind-Up Zenmaines",
      "Copies": 1
    }
  ],
  "SideDeck": [
    {
      "Name": "D.D. Crow",
      "Copies": 1
    },
    {
      "Name": "Neo-Spacian Grand Mole",
      "Copies": 1
    },
    {
      "Name": "Satellarknight Alsahm",
      "Copies": 1
    },
    {
      "Name": "Thunder King Rai-Oh",
      "Copies": 1
    },
    {
      "Name": "Trap Eater",
      "Copies": 3
    },
    {
      "Name": "Dimensional Fissure",
      "Copies": 1
    },
    {
      "Name": "Mystical Space Typhoon",
      "Copies": 1
    },
    {
      "Name": "Shadow-Imprisoning Mirror",
      "Copies": 3
    },
    {
      "Name": "Stygian Dirge",
      "Copies": 3
    }
  ]
}