{
  "Date": "June 2017",
  "Tournament": "ARGCS - Atlanta Georgia",
  "DeckName": "True Draco Zoodiacs",
  "DeckId": "6578",
  "Duelist": "Norma Irfan",
  "Placed": "9th - 16th Place",
  "Archetype": "True Draco",
  "DeckProfile": "",
  "MainDeck": [
    {
      "Name": "Ash Blossom & Joyous Spring",
      "Copies": 3
    },
    {
      "Name": "Baobaboon",
      "Copies": 3
    },
    {
      "Name": "Blackwing - Zephyros the Elite",
      "Copies": 1
    },
    {
      "Name": "Ghost Ogre & Snow Rabbit",
      "Copies": 3
    },
    {
      "Name": "Master Peace, the True Dracoslaying King",
      "Copies": 2
    },
    {
      "Name": "Maxx \"C\"",
      "Copies": 1
    },
    {
      "Name": "Zoodiac Ramram",
      "Copies": 2
    },
    {
      "Name": "Zoodiac Ratpier",
      "Copies": 2
    },
    {
      "Name": "Zoodiac Thoroughblade",
      "Copies": 1
    },
    {
      "Name": "Zoodiac Whiptail",
      "Copies": 2
    },
    {
      "Name": "Dragonic Diagram",
      "Copies": 3
    },
    {
      "Name": "Fire Formation - Tenki",
      "Copies": 3
    },
    {
      "Name": "My Body as a Shield",
      "Copies": 2
    },
    {
      "Name": "Terraforming",
      "Copies": 3
    },
    {
      "Name": "True Draco Heritage",
      "Copies": 1
    },
    {
      "Name": "Zoodiac Barrage",
      "Copies": 3
    },
    {
      "Name": "Dimensional Barrier",
      "Copies": 3
    },
    {
      "Name": "True King's Return",
      "Copies": 1
    },
    {
      "Name": "Zoodiac Combo",
      "Copies": 1
    }
  ],
  "ExtraDeck": [
    {
      "Name": "Daigusto Emeral",
      "Copies": 2
    },
    {
      "Name": "Gagaga Samurai",
      "Copies": 1
    },
    {
      "Name": "M-X-Saber Invoker",
      "Copies": 1
    },
    {
      "Name": "Raidraptor - Force Strix",
      "Copies": 1
    },
    {
      "Name": "Tornado Dragon",
      "Copies": 1
    },
    {
      "Name": "Zoodiac Boarbow",
      "Copies": 1
    },
    {
      "Name": "Zoodiac Broadbull",
      "Copies": 2
    },
    {
      "Name": "Zoodiac Chakanine",
      "Copies": 2
    },
    {
      "Name": "Zoodiac Drident",
      "Copies": 2
    },
    {
      "Name": "Zoodiac Hammerkong",
      "Copies": 1
    },
    {
      "Name": "Zoodiac Tigermortar",
      "Copies": 1
    }
  ],
  "SideDeck": [
    {
      "Name": "Gameciel, the Sea Turtle Kaiju",
      "Copies": 2
    },
    {
      "Name": "Kumongous, the Sticky String Kaiju",
      "Copies": 1
    },
    {
      "Name": "M-Warrior 1",
      "Copies": 3
    },
    {
      "Name": "Dark Hole",
      "Copies": 2
    },
    {
      "Name": "Forbidden Chalice",
      "Copies": 3
    },
    {
      "Name": "Raigeki",
      "Copies": 1
    },
    {
      "Name": "Anti-Spell Fragrance",
      "Copies": 2
    },
    {
      "Name": "Imperial Order",
      "Copies": 1
    }
  ]
}